Workbook

Sheet Dashboard
A1: Dashboard das Contas — out/26 a dez/27
A2: Escolha o mês na célula amarela (B4). Tudo atualiza sozinho a partir das outras abas.
A4: Mês: | B4: 46296 | D4: =INDEX(Resumo!$S$5:$S$19,MATCH($B$4,Resumo!$A$5:$A$19,0)) -> NO VERMELHO
A6: Receita p/ contas | C6: Total comprometido | E6: SOBRA | G6: % comprometido
A7: =INDEX(Resumo!$B$5:$B$19,MATCH($B$4,Resumo!$A$5:$A$19,0)) -> 5700 | C7: =INDEX(Resumo!$H$5:$H$19,MATCH($B$4,Resumo!$A$5:$A$19,0)) -> 9053.22 | E7: =INDEX(Resumo!$I$5:$I$19,MATCH($B$4,Resumo!$A$5:$A$19,0)) -> -3353.22 | G7: =INDEX(Resumo!$J$5:$J$19,MATCH($B$4,Resumo!$A$5:$A$19,0)) -> 1.5882842
A9: Guardar (meta) | C9: Reserva novas coisas | E9: LIVRE p/ gastar | G9: Saldo acumulado
A10: =INDEX(Resumo!$L$5:$L$19,MATCH($B$4,Resumo!$A$5:$A$19,0)) -> 0 | C10: =INDEX(Resumo!$M$5:$M$19,MATCH($B$4,Resumo!$A$5:$A$19,0)) -> 0 | E10: =INDEX(Resumo!$N$5:$N$19,MATCH($B$4,Resumo!$A$5:$A$19,0)) -> 0 | G10: =INDEX(Resumo!$O$5:$O$19,MATCH($B$4,Resumo!$A$5:$A$19,0)) -> -3353.22
A13: Para onde vai o dinheiro no mês
A14: Categoria | B14: Valor | C14: % da receita
A15: Contas fixas | B15: =INDEX(Resumo!$C$5:$C$19,MATCH($B$4,Resumo!$A$5:$A$19,0)) -> 2469.23 | C15: =IF($A$7=0,0,B15/$A$7) -> 0.43319825
A16: Cartão (parcelas antigas) | B16: =INDEX(Resumo!$D$5:$D$19,MATCH($B$4,Resumo!$A$5:$A$19,0)) -> 6583.99 | C16: =IF($A$7=0,0,B16/$A$7) -> 1.155086
A17: Cartão (compras novas) | B17: =INDEX(Resumo!$E$5:$E$19,MATCH($B$4,Resumo!$A$5:$A$19,0)) -> 0 | C17: =IF($A$7=0,0,B17/$A$7) -> 0
A18: Mercado (do salário) | B18: =INDEX(Resumo!$F$5:$F$19,MATCH($B$4,Resumo!$A$5:$A$19,0)) -> 0 | C18: =IF($A$7=0,0,B18/$A$7) -> 0
A19: Provisões IPTU/IPVA | B19: =INDEX(Resumo!$G$5:$G$19,MATCH($B$4,Resumo!$A$5:$A$19,0)) -> 0 | C19: =IF($A$7=0,0,B19/$A$7) -> 0
A20: Cobrir mês negativo | B20: =INDEX(Resumo!$K$5:$K$19,MATCH($B$4,Resumo!$A$5:$A$19,0)) -> 0 | C20: =IF($A$7=0,0,B20/$A$7) -> 0
A21: Guardar (meta) | B21: =INDEX(Resumo!$L$5:$L$19,MATCH($B$4,Resumo!$A$5:$A$19,0)) -> 0 | C21: =IF($A$7=0,0,B21/$A$7) -> 0
A22: Reserva novas coisas | B22: =INDEX(Resumo!$M$5:$M$19,MATCH($B$4,Resumo!$A$5:$A$19,0)) -> 0 | C22: =IF($A$7=0,0,B22/$A$7) -> 0
A23: Livre p/ gastar | B23: =INDEX(Resumo!$N$5:$N$19,MATCH($B$4,Resumo!$A$5:$A$19,0)) -> 0 | C23: =IF($A$7=0,0,B23/$A$7) -> 0
A25: Mês NO VERMELHO = sobra negativa. Use bônus (aba Receitas) ou o saldo acumulado dos meses seguintes.

Sheet Resumo
A1: Resumo mensal (automático)
A2: Tudo aqui é calculado a partir das outras abas. Não precisa editar.
A4: Mês | B4: Receita p/ contas | C4: Contas fixas | D4: Cartão (parcelas antigas) | E4: Cartão (compras novas) | F4: Mercado (do salário) | G4: Provisões IPTU/IPVA | H4: TOTAL COMPROMETIDO | I4: SOBRA | J4: % comprometido | K4: Cobrir mês negativo | L4: Guardar (meta) | M4: Reserva novas coisas | N4: LIVRE p/ gastar | O4: Saldo acumulado | P4: Guardado de verdade | Q4: Alelo | R4: Bônus reservado | S4: Status
A5: 46296 | B5: =Receitas!D11 -> 5700 | C5: ='Contas Fixas'!D25 -> 2469.23 | D5: =Cartão!D5+Cartão!D6 -> 6583.99 | E5: =Cartão!D7+Cartão!D8 -> 0 | F5: ='Mercado & Alelo'!D8 -> 0 | G5: =Provisões!B24 -> 0 | H5: =SUM(C5:G5) -> 9053.22 | I5: =B5-H5 -> -3353.22 | J5: =IF(B5=0,0,H5/B5) -> 1.5882842 | K5: =0 -> 0 | L5: =MAX(0,I5-K5)*Config!$B$5 -> 0 | M5: =MAX(0,I5-K5)*Config!$B$6 -> 0 | N5: =MAX(0,I5-K5)*Config!$B$7 -> 0 | O5: =I5 -> -3353.22 | P5: =Metas!B20 -> 0 | Q5: ='Mercado & Alelo'!D6 -> 0 | R5: =Receitas!D10 -> 0 | S5: =IF(I5<0,"NO VERMELHO",IF(K5>0,"PAGANDO BURACO",IF(J5>Config!$B$8,"ALERTA","OK"))) -> NO VERMELHO
A6: 46327 | B6: =Receitas!E11 -> 5700 | C6: ='Contas Fixas'!E25 -> 2469.23 | D6: =Cartão!E5+Cartão!E6 -> 2372 | E6: =Cartão!E7+Cartão!E8 -> 0 | F6: ='Mercado & Alelo'!E8 -> 0 | G6: =Provisões!C24 -> 316.66667 | H6: =SUM(C6:G6) -> 5157.8967 | I6: =B6-H6 -> 542.10333 | J6: =IF(B6=0,0,H6/B6) -> 0.90489415 | K6: =IF(AND(I6>0,O5<0),MIN(I6,-O5),0) -> 542.10333 | L6: =MAX(0,I6-K6)*Config!$B$5 -> 0 | M6: =MAX(0,I6-K6)*Config!$B$6 -> 0 | N6: =MAX(0,I6-K6)*Config!$B$7 -> 0 | O6: =O5+I6 -> -2811.1167 | P6: =Metas!C20 -> 0 | Q6: ='Mercado & Alelo'!E6 -> 0 | R6: =Receitas!E10 -> 0 | S6: =IF(I6<0,"NO VERMELHO",IF(K6>0,"PAGANDO BURACO",IF(J6>Config!$B$8,"ALERTA","OK"))) -> PAGANDO BURACO
A7: 46357 | B7: =Receitas!F11 -> 5700 | C7: ='Contas Fixas'!F25 -> 2409.23 | D7: =Cartão!F5+Cartão!F6 -> 1487.5 | E7: =Cartão!F7+Cartão!F8 -> 0 | F7: ='Mercado & Alelo'!F8 -> 0 | G7: =Provisões!D24 -> 316.66667 | H7: =SUM(C7:G7) -> 4213.3967 | I7: =B7-H7 -> 1486.6033 | J7: =IF(B7=0,0,H7/B7) -> 0.7391924 | K7: =IF(AND(I7>0,O6<0),MIN(I7,-O6),0) -> 1486.6033 | L7: =MAX(0,I7-K7)*Config!$B$5 -> 0 | M7: =MAX(0,I7-K7)*Config!$B$6 -> 0 | N7: =MAX(0,I7-K7)*Config!$B$7 -> 0 | O7: =O6+I7 -> -1324.5133 | P7: =Metas!D20 -> 0 | Q7: ='Mercado & Alelo'!F6 -> 0 | R7: =Receitas!F10 -> 0 | S7: =IF(I7<0,"NO VERMELHO",IF(K7>0,"PAGANDO BURACO",IF(J7>Config!$B$8,"ALERTA","OK"))) -> PAGANDO BURACO
A8: 46388 | B8: =Receitas!G11 -> 5700 | C8: ='Contas Fixas'!G25 -> 2409.23 | D8: =Cartão!G5+Cartão!G6 -> 1042.78 | E8: =Cartão!G7+Cartão!G8 -> 0 | F8: ='Mercado & Alelo'!G8 -> 0 | G8: =Provisões!E24 -> 316.66667 | H8: =SUM(C8:G8) -> 3768.6767 | I8: =B8-H8 -> 1931.3233 | J8: =IF(B8=0,0,H8/B8) -> 0.66117135 | K8: =IF(AND(I8>0,O7<0),MIN(I8,-O7),0) -> 1324.5133 | L8: =MAX(0,I8-K8)*Config!$B$5 -> 182.043 | M8: =MAX(0,I8-K8)*Config!$B$6 -> 121.362 | N8: =MAX(0,I8-K8)*Config!$B$7 -> 303.405 | O8: =O7+I8 -> 606.81 | P8: =Metas!E20 -> 0 | Q8: ='Mercado & Alelo'!G6 -> 0 | R8: =Receitas!G10 -> 0 | S8: =IF(I8<0,"NO VERMELHO",IF(K8>0,"PAGANDO BURACO",IF(J8>Config!$B$8,"ALERTA","OK"))) -> PAGANDO BURACO
A9: 46419 | B9: =Receitas!H11 -> 5700 | C9: ='Contas Fixas'!H25 -> 2409.23 | D9: =Cartão!H5+Cartão!H6 -> 704.13 | E9: =Cartão!H7+Cartão!H8 -> 0 | F9: ='Mercado & Alelo'!H8 -> 0 | G9: =Provisões!F24 -> 200 | H9: =SUM(C9:G9) -> 3313.36 | I9: =B9-H9 -> 2386.64 | J9: =IF(B9=0,0,H9/B9) -> 0.58129123 | K9: =IF(AND(I9>0,O8<0),MIN(I9,-O8),0) -> 0 | L9: =MAX(0,I9-K9)*Config!$B$5 -> 715.992 | M9: =MAX(0,I9-K9)*Config!$B$6 -> 477.328 | N9: =MAX(0,I9-K9)*Config!$B$7 -> 1193.32 | O9: =O8+I9 -> 2993.45 | P9: =Metas!F20 -> 0 | Q9: ='Mercado & Alelo'!H6 -> 0 | R9: =Receitas!H10 -> 0 | S9: =IF(I9<0,"NO VERMELHO",IF(K9>0,"PAGANDO BURACO",IF(J9>Config!$B$8,"ALERTA","OK"))) -> OK
A10: 46447 | B10: =Receitas!I11 -> 5700 | C10: ='Contas Fixas'!I25 -> 2409.23 | D10: =Cartão!I5+Cartão!I6 -> 666.45 | E10: =Cartão!I7+Cartão!I8 -> 0 | F10: ='Mercado & Alelo'!I8 -> 0 | G10: =Provisões!G24 -> 0 | H10: =SUM(C10:G10) -> 3075.68 | I10: =B10-H10 -> 2624.32 | J10: =IF(B10=0,0,H10/B10) -> 0.53959298 | K10: =IF(AND(I10>0,O9<0),MIN(I10,-O9),0) -> 0 | L10: =MAX(0,I10-K10)*Config!$B$5 -> 787.296 | M10: =MAX(0,I10-K10)*Config!$B$6 -> 524.864 | N10: =MAX(0,I10-K10)*Config!$B$7 -> 1312.16 | O10: =O9+I10 -> 5617.77 | P10: =Metas!G20 -> 0 | Q10: ='Mercado & Alelo'!I6 -> 0 | R10: =Receitas!I10 -> 0 | S10: =IF(I10<0,"NO VERMELHO",IF(K10>0,"PAGANDO BURACO",IF(J10>Config!$B$8,"ALERTA","OK"))) -> OK
A11: 46478 | B11: =Receitas!J11 -> 5700 | C11: ='Contas Fixas'!J25 -> 2409.23 | D11: =Cartão!J5+Cartão!J6 -> 540.62 | E11: =Cartão!J7+Cartão!J8 -> 0 | F11: ='Mercado & Alelo'!J8 -> 0 | G11: =Provisões!H24 -> 0 | H11: =SUM(C11:G11) -> 2949.85 | I11: =B11-H11 -> 2750.15 | J11: =IF(B11=0,0,H11/B11) -> 0.51751754 | K11: =IF(AND(I11>0,O10<0),MIN(I11,-O10),0) -> 0 | L11: =MAX(0,I11-K11)*Config!$B$5 -> 825.045 | M11: =MAX(0,I11-K11)*Config!$B$6 -> 550.03 | N11: =MAX(0,I11-K11)*Config!$B$7 -> 1375.075 | O11: =O10+I11 -> 8367.92 | P11: =Metas!H20 -> 0 | Q11: ='Mercado & Alelo'!J6 -> 0 | R11: =Receitas!J10 -> 0 | S11: =IF(I11<0,"NO VERMELHO",IF(K11>0,"PAGANDO BURACO",IF(J11>Config!$B$8,"ALERTA","OK"))) -> OK
A12: 46508 | B12: =Receitas!K11 -> 5700 | C12: ='Contas Fixas'!K25 -> 2409.23 | D12: =Cartão!K5+Cartão!K6 -> 540.62 | E12: =Cartão!K7+Cartão!K8 -> 0 | F12: ='Mercado & Alelo'!K8 -> 0 | G12: =Provisões!I24 -> 0 | H12: =SUM(C12:G12) -> 2949.85 | I12: =B12-H12 -> 2750.15 | J12: =IF(B12=0,0,H12/B12) -> 0.51751754 | K12: =IF(AND(I12>0,O11<0),MIN(I12,-O11),0) -> 0 | L12: =MAX(0,I12-K12)*Config!$B$5 -> 825.045 | M12: =MAX(0,I12-K12)*Config!$B$6 -> 550.03 | N12: =MAX(0,I12-K12)*Config!$B$7 -> 1375.075 | O12: =O11+I12 -> 11118.07 | P12: =Metas!I20 -> 0 | Q12: ='Mercado & Alelo'!K6 -> 0 | R12: =Receitas!K10 -> 0 | S12: =IF(I12<0,"NO VERMELHO",IF(K12>0,"PAGANDO BURACO",IF(J12>Config!$B$8,"ALERTA","OK"))) -> OK
A13: 46539 | B13: =Receitas!L11 -> 5700 | C13: ='Contas Fixas'!L25 -> 2409.23 | D13: =Cartão!L5+Cartão!L6 -> 75.48 | E13: =Cartão!L7+Cartão!L8 -> 0 | F13: ='Mercado & Alelo'!L8 -> 0 | G13: =Provisões!J24 -> 0 | H13: =SUM(C13:G13) -> 2484.71 | I13: =B13-H13 -> 3215.29 | J13: =IF(B13=0,0,H13/B13) -> 0.43591404 | K13: =IF(AND(I13>0,O12<0),MIN(I13,-O12),0) -> 0 | L13: =MAX(0,I13-K13)*Config!$B$5 -> 964.587 | M13: =MAX(0,I13-K13)*Config!$B$6 -> 643.058 | N13: =MAX(0,I13-K13)*Config!$B$7 -> 1607.645 | O13: =O12+I13 -> 14333.36 | P13: =Metas!J20 -> 0 | Q13: ='Mercado & Alelo'!L6 -> 0 | R13: =Receitas!L10 -> 0 | S13: =IF(I13<0,"NO VERMELHO",IF(K13>0,"PAGANDO BURACO",IF(J13>Config!$B$8,"ALERTA","OK"))) -> OK
A14: 46569 | B14: =Receitas!M11 -> 5700 | C14: ='Contas Fixas'!M25 -> 2409.23 | D14: =Cartão!M5+Cartão!M6 -> 23.07 | E14: =Cartão!M7+Cartão!M8 -> 0 | F14: ='Mercado & Alelo'!M8 -> 0 | G14: =Provisões!K24 -> 0 | H14: =SUM(C14:G14) -> 2432.3 | I14: =B14-H14 -> 3267.7 | J14: =IF(B14=0,0,H14/B14) -> 0.4267193 | K14: =IF(AND(I14>0,O13<0),MIN(I14,-O13),0) -> 0 | L14: =MAX(0,I14-K14)*Config!$B$5 -> 980.31 | M14: =MAX(0,I14-K14)*Config!$B$6 -> 653.54 | N14: =MAX(0,I14-K14)*Config!$B$7 -> 1633.85 | O14: =O13+I14 -> 17601.06 | P14: =Metas!K20 -> 0 | Q14: ='Mercado & Alelo'!M6 -> 0 | R14: =Receitas!M10 -> 0 | S14: =IF(I14<0,"NO VERMELHO",IF(K14>0,"PAGANDO BURACO",IF(J14>Config!$B$8,"ALERTA","OK"))) -> OK
A15: 46600 | B15: =Receitas!N11 -> 5700 | C15: ='Contas Fixas'!N25 -> 2409.23 | D15: =Cartão!N5+Cartão!N6 -> 0 | E15: =Cartão!N7+Cartão!N8 -> 0 | F15: ='Mercado & Alelo'!N8 -> 0 | G15: =Provisões!L24 -> 0 | H15: =SUM(C15:G15) -> 2409.23 | I15: =B15-H15 -> 3290.77 | J15: =IF(B15=0,0,H15/B15) -> 0.42267193 | K15: =IF(AND(I15>0,O14<0),MIN(I15,-O14),0) -> 0 | L15: =MAX(0,I15-K15)*Config!$B$5 -> 987.231 | M15: =MAX(0,I15-K15)*Config!$B$6 -> 658.154 | N15: =MAX(0,I15-K15)*Config!$B$7 -> 1645.385 | O15: =O14+I15 -> 20891.83 | P15: =Metas!L20 -> 0 | Q15: ='Mercado & Alelo'!N6 -> 0 | R15: =Receitas!N10 -> 0 | S15: =IF(I15<0,"NO VERMELHO",IF(K15>0,"PAGANDO BURACO",IF(J15>Config!$B$8,"ALERTA","OK"))) -> OK
A16: 46631 | B16: =Receitas!O11 -> 5700 | C16: ='Contas Fixas'!O25 -> 2409.23 | D16: =Cartão!O5+Cartão!O6 -> 0 | E16: =Cartão!O7+Cartão!O8 -> 0 | F16: ='Mercado & Alelo'!O8 -> 0 | G16: =Provisões!M24 -> 0 | H16: =SUM(C16:G16) -> 2409.23 | I16: =B16-H16 -> 3290.77 | J16: =IF(B16=0,0,H16/B16) -> 0.42267193 | K16: =IF(AND(I16>0,O15<0),MIN(I16,-O15),0) -> 0 | L16: =MAX(0,I16-K16)*Config!$B$5 -> 987.231 | M16: =MAX(0,I16-K16)*Config!$B$6 -> 658.154 | N16: =MAX(0,I16-K16)*Config!$B$7 -> 1645.385 | O16: =O15+I16 -> 24182.6 | P16: =Metas!M20 -> 0 | Q16: ='Mercado & Alelo'!O6 -> 0 | R16: =Receitas!O10 -> 0 | S16: =IF(I16<0,"NO VERMELHO",IF(K16>0,"PAGANDO BURACO",IF(J16>Config!$B$8,"ALERTA","OK"))) -> OK
A17: 46661 | B17: =Receitas!P11 -> 5700 | C17: ='Contas Fixas'!P25 -> 2409.23 | D17: =Cartão!P5+Cartão!P6 -> 0 | E17: =Cartão!P7+Cartão!P8 -> 0 | F17: ='Mercado & Alelo'!P8 -> 0 | G17: =Provisões!N24 -> 0 | H17: =SUM(C17:G17) -> 2409.23 | I17: =B17-H17 -> 3290.77 | J17: =IF(B17=0,0,H17/B17) -> 0.42267193 | K17: =IF(AND(I17>0,O16<0),MIN(I17,-O16),0) -> 0 | L17: =MAX(0,I17-K17)*Config!$B$5 -> 987.231 | M17: =MAX(0,I17-K17)*Config!$B$6 -> 658.154 | N17: =MAX(0,I17-K17)*Config!$B$7 -> 1645.385 | O17: =O16+I17 -> 27473.37 | P17: =Metas!N20 -> 0 | Q17: ='Mercado & Alelo'!P6 -> 0 | R17: =Receitas!P10 -> 0 | S17: =IF(I17<0,"NO VERMELHO",IF(K17>0,"PAGANDO BURACO",IF(J17>Config!$B$8,"ALERTA","OK"))) -> OK
A18: 46692 | B18: =Receitas!Q11 -> 5700 | C18: ='Contas Fixas'!Q25 -> 2409.23 | D18: =Cartão!Q5+Cartão!Q6 -> 0 | E18: =Cartão!Q7+Cartão!Q8 -> 0 | F18: ='Mercado & Alelo'!Q8 -> 0 | G18: =Provisões!O24 -> 0 | H18: =SUM(C18:G18) -> 2409.23 | I18: =B18-H18 -> 3290.77 | J18: =IF(B18=0,0,H18/B18) -> 0.42267193 | K18: =IF(AND(I18>0,O17<0),MIN(I18,-O17),0) -> 0 | L18: =MAX(0,I18-K18)*Config!$B$5 -> 987.231 | M18: =MAX(0,I18-K18)*Config!$B$6 -> 658.154 | N18: =MAX(0,I18-K18)*Config!$B$7 -> 1645.385 | O18: =O17+I18 -> 30764.14 | P18: =Metas!O20 -> 0 | Q18: ='Mercado & Alelo'!Q6 -> 0 | R18: =Receitas!Q10 -> 0 | S18: =IF(I18<0,"NO VERMELHO",IF(K18>0,"PAGANDO BURACO",IF(J18>Config!$B$8,"ALERTA","OK"))) -> OK
A19: 46722 | B19: =Receitas!R11 -> 5700 | C19: ='Contas Fixas'!R25 -> 2409.23 | D19: =Cartão!R5+Cartão!R6 -> 0 | E19: =Cartão!R7+Cartão!R8 -> 0 | F19: ='Mercado & Alelo'!R8 -> 0 | G19: =Provisões!P24 -> 0 | H19: =SUM(C19:G19) -> 2409.23 | I19: =B19-H19 -> 3290.77 | J19: =IF(B19=0,0,H19/B19) -> 0.42267193 | K19: =IF(AND(I19>0,O18<0),MIN(I19,-O18),0) -> 0 | L19: =MAX(0,I19-K19)*Config!$B$5 -> 987.231 | M19: =MAX(0,I19-K19)*Config!$B$6 -> 658.154 | N19: =MAX(0,I19-K19)*Config!$B$7 -> 1645.385 | O19: =O18+I19 -> 34054.91 | P19: =Metas!P20 -> 0 | Q19: ='Mercado & Alelo'!R6 -> 0 | R19: =Receitas!R10 -> 0 | S19: =IF(I19<0,"NO VERMELHO",IF(K19>0,"PAGANDO BURACO",IF(J19>Config!$B$8,"ALERTA","OK"))) -> OK
A20: TOTAL | B20: =SUM(B5:B19) -> 85500 | C20: =SUM(C5:C19) -> 36258.45 | D20: =SUM(D5:D19) -> 14036.64 | E20: =SUM(E5:E19) -> 0 | F20: =SUM(F5:F19) -> 0 | G20: =SUM(G5:G19) -> 1150 | H20: =SUM(H5:H19) -> 51445.09 | I20: =SUM(I5:I19) -> 34054.91 | J20: =IF(B20=0,0,H20/B20) -> 0.60169696 | K20: =SUM(K5:K19) -> 3353.22 | L20: =SUM(L5:L19) -> 10216.473 | M20: =SUM(M5:M19) -> 6810.982 | N20: =SUM(N5:N19) -> 17027.455 | O20: =O19 -> 34054.91 | P20: =SUM(P5:P19) -> 0 | Q20: =SUM(Q5:Q19) -> 0 | R20: =SUM(R5:R19) -> 0

Sheet Receitas
A1: Receitas (entradas do mês)
A2: Células AMARELAS com texto AZUL = você preenche/edita. O resto é fórmula (não apague). Bônus: lance o valor recebido e quanto dele vai para as contas.
A4: Item | B4: Categoria | C4: Obs. | D4: 46296 | E4: 46327 | F4: 46357 | G4: 46388 | H4: 46419 | I4: 46447 | J4: 46478 | K4: 46508 | L4: 46539 | M4: 46569 | N4: 46600 | O4: 46631 | P4: 46661 | Q4: 46692 | R4: 46722 | S4: Total
A5: Salário Jessica | B5: Salário | C5: fixo | D5: 3000 | E5: 3000 | F5: 3000 | G5: 3000 | H5: 3000 | I5: 3000 | J5: 3000 | K5: 3000 | L5: 3000 | M5: 3000 | N5: 3000 | O5: 3000 | P5: 3000 | Q5: 3000 | R5: 3000 | S5: =SUM(D5:R5) -> 45000
A6: Salário Pedro | B6: Salário | C6: aprox. | D6: 2700 | E6: 2700 | F6: 2700 | G6: 2700 | H6: 2700 | I6: 2700 | J6: 2700 | K6: 2700 | L6: 2700 | M6: 2700 | N6: 2700 | O6: 2700 | P6: 2700 | Q6: 2700 | R6: 2700 | S6: =SUM(D6:R6) -> 40500
A7: Bônus Jessica - recebido | B7: Bônus | C7: quando houver | D7: 0 | E7: 0 | F7: 0 | G7: 0 | H7: 0 | I7: 0 | J7: 0 | K7: 0 | L7: 0 | M7: 0 | N7: 0 | O7: 0 | P7: 0 | Q7: 0 | R7: 0 | S7: =SUM(D7:R7) -> 0
A8: Bônus - usado nas contas | B8: Bônus | C8: parte do bônus p/ as contas | D8: 0 | E8: 0 | F8: 0 | G8: 0 | H8: 0 | I8: 0 | J8: 0 | K8: 0 | L8: 0 | M8: 0 | N8: 0 | O8: 0 | P8: 0 | Q8: 0 | R8: 0 | S8: =SUM(D8:R8) -> 0
A9: Outras entradas | B9: Outros | C9: freelas, vendas... | D9: 0 | E9: 0 | F9: 0 | G9: 0 | H9: 0 | I9: 0 | J9: 0 | K9: 0 | L9: 0 | M9: 0 | N9: 0 | O9: 0 | P9: 0 | Q9: 0 | R9: 0 | S9: =SUM(D9:R9) -> 0
A10: Bônus guardado p/ coisas específicas | D10: =MAX(0,D7-D8) -> 0 | E10: =MAX(0,E7-E8) -> 0 | F10: =MAX(0,F7-F8) -> 0 | G10: =MAX(0,G7-G8) -> 0 | H10: =MAX(0,H7-H8) -> 0 | I10: =MAX(0,I7-I8) -> 0 | J10: =MAX(0,J7-J8) -> 0 | K10: =MAX(0,K7-K8) -> 0 | ... R10: =MAX(0,R7-R8) -> 0 | S10: =SUM(D10:R10) -> 0
A11: RECEITA PARA AS CONTAS | D11: =D5+D6+MIN(D7,D8)+D9 -> 5700 | E11: =E5+E6+MIN(E7,E8)+E9 -> 5700 | F11: =F5+F6+MIN(F7,F8)+F9 -> 5700 | G11: =G5+G6+MIN(G7,G8)+G9 -> 5700 | H11: =H5+H6+MIN(H7,H8)+H9 -> 5700 | I11: =I5+I6+MIN(I7,I8)+I9 -> 5700 | J11: =J5+J6+MIN(J7,J8)+J9 -> 5700 | K11: =K5+K6+MIN(K7,K8)+K9 -> 5700 | ... S11: =S5+S6+MIN(S7,S8)+S9 -> 85500
A13: Obs.: o salário do Pedro (~R$ 2.700) é aproximado — ajuste mês a mês quando souber o valor real.

Sheet Contas Fixas
A1: Contas fixas
A2: Células AMARELAS com texto AZUL = você preenche/edita. O resto é fórmula (não apague). Conta nova: use as linhas em branco. Valor mudou (ex.: DAS 2027)? Edite daquele mês em diante.
A4: Item | B4: Categoria | C4: Obs. | D4: 46296 | E4: 46327 | F4: 46357 | G4: 46388 | H4: 46419 | I4: 46447 | J4: 46478 | K4: 46508 | L4: 46539 | M4: 46569 | N4: 46600 | O4: 46631 | P4: 46661 | Q4: 46692 | R4: 46722 | S4: Total
A5: Casa | B5: Moradia | C5: aprox. | D5: 1350 | E5: 1350 | F5: 1350 | G5: 1350 | H5: 1350 | I5: 1350 | J5: 1350 | K5: 1350 | L5: 1350 | M5: 1350 | N5: 1350 | O5: 1350 | P5: 1350 | Q5: 1350 | R5: 1350 | S5: =SUM(D5:R5) -> 20250
A6: TIM | B6: Telefone/Internet | C6: aprox. | D6: 54.7 | E6: 54.7 | F6: 54.7 | G6: 54.7 | H6: 54.7 | I6: 54.7 | J6: 54.7 | K6: 54.7 | L6: 54.7 | M6: 54.7 | N6: 54.7 | O6: 54.7 | P6: 54.7 | Q6: 54.7 | R6: 54.7 | S6: =SUM(D6:R6) -> 820.5
A7: DAS | B7: Impostos | C7: vai aumentar em 2027 | D7: 86.5 | E7: 86.5 | F7: 86.5 | G7: 86.5 | H7: 86.5 | I7: 86.5 | J7: 86.5 | K7: 86.5 | L7: 86.5 | M7: 86.5 | N7: 86.5 | O7: 86.5 | P7: 86.5 | Q7: 86.5 | R7: 86.5 | S7: =SUM(D7:R7) -> 1297.5
A8: Internet | B8: Telefone/Internet | C8: vai aumentar | D8: 119.9 | E8: 119.9 | F8: 119.9 | G8: 119.9 | H8: 119.9 | I8: 119.9 | J8: 119.9 | K8: 119.9 | L8: 119.9 | M8: 119.9 | N8: 119.9 | O8: 119.9 | P8: 119.9 | Q8: 119.9 | R8: 119.9 | S8: =SUM(D8:R8) -> 1798.5
A9: Água | B9: Moradia | C9: aprox. | D9: 110 | E9: 110 | F9: 110 | G9: 110 | H9: 110 | I9: 110 | J9: 110 | K9: 110 | L9: 110 | M9: 110 | N9: 110 | O9: 110 | P9: 110 | Q9: 110 | R9: 110 | S9: =SUM(D9:R9) -> 1650
A10: Luz | B10: Moradia | C10: média R$ 200-240 | D10: 220 | E10: 220 | F10: 220 | G10: 220 | H10: 220 | I10: 220 | J10: 220 | K10: 220 | L10: 220 | M10: 220 | N10: 220 | O10: 220 | P10: 220 | Q10: 220 | R10: 220 | S10: =SUM(D10:R10) -> 3300
A11: Moto (parcela) | B11: Transporte | C11: até dez/27 | D11: 433.13 | E11: 433.13 | F11: 433.13 | G11: 433.13 | H11: 433.13 | I11: 433.13 | J11: 433.13 | K11: 433.13 | L11: 433.13 | M11: 433.13 | N11: 433.13 | O11: 433.13 | P11: 433.13 | Q11: 433.13 | R11: 433.13 | S11: =SUM(D11:R11) -> 6496.95
A12: Renner | B12: Compras | C12: últimas parcelas | D12: 60 | E12: 60 | F12: 0 | G12: 0 | H12: 0 | I12: 0 | J12: 0 | K12: 0 | L12: 0 | M12: 0 | N12: 0 | O12: 0 | P12: 0 | Q12: 0 | R12: 0 | S12: =SUM(D12:R12) -> 120
A13: Roupinha | B13: Compras | C13: mensal | D13: 35 | E13: 35 | F13: 35 | G13: 35 | H13: 35 | I13: 35 | J13: 35 | K13: 35 | L13: 35 | M13: 35 | N13: 35 | O13: 35 | P13: 35 | Q13: 35 | R13: 35 | S13: =SUM(D13:R13) -> 525
S14: =SUM(D14:R14) -> 0
S15: =SUM(D15:R15) -> 0
S16: =SUM(D16:R16) -> 0
S17: =SUM(D17:R17) -> 0
S18: =SUM(D18:R18) -> 0
S19: =SUM(D19:R19) -> 0
S20: =SUM(D20:R20) -> 0
S21: =SUM(D21:R21) -> 0
S22: =SUM(D22:R22) -> 0
S23: =SUM(D23:R23) -> 0
S24: =SUM(D24:R24) -> 0
A25: TOTAL CONTAS FIXAS | D25: =SUM(D5:D24) -> 2469.23 | E25: =SUM(E5:E24) -> 2469.23 | F25: =SUM(F5:F24) -> 2409.23 | G25: =SUM(G5:G24) -> 2409.23 | H25: =SUM(H5:H24) -> 2409.23 | I25: =SUM(I5:I24) -> 2409.23 | J25: =SUM(J5:J24) -> 2409.23 | K25: =SUM(K5:K24) -> 2409.23 | ... S25: =SUM(S5:S24) -> 36258.45

Sheet Cartão
A1: Cartão de crédito — parcelas por mês
A2: Células AMARELAS com texto AZUL = você preenche/edita. O resto é fórmula (não apague). Linhas 5-6 = parcelas que já existiam. Linhas 7-8 vêm sozinhas da aba 'Compras Cartão'.
A4: Item | B4: Categoria | C4: Obs. | D4: 46296 | E4: 46327 | F4: 46357 | G4: 46388 | H4: 46419 | I4: 46447 | J4: 46478 | K4: 46508 | L4: 46539 | M4: 46569 | N4: 46600 | O4: 46631 | P4: 46661 | Q4: 46692 | R4: 46722 | S4: Total
A5: Parcelas já existentes - Jessica | B5: Cartão | D5: 3126.15 | E5: 1319.86 | F5: 659.7 | G5: 365.14 | H5: 81.48 | I5: 52.41 | J5: 52.41 | K5: 52.41 | L5: 52.41 | M5: 0 | N5: 0 | O5: 0 | P5: 0 | Q5: 0 | R5: 0 | S5: =SUM(D5:R5) -> 5761.97
A6: Parcelas já existentes - Pedro | B6: Cartão | D6: 3457.84 | E6: 1052.14 | F6: 827.8 | G6: 677.64 | H6: 622.65 | I6: 614.04 | J6: 488.21 | K6: 488.21 | L6: 23.07 | M6: 23.07 | N6: 0 | O6: 0 | P6: 0 | Q6: 0 | R6: 0 | S6: =SUM(D6:R6) -> 8274.67
A7: Novas compras - Jessica | B7: Cartão | C7: automático | D7: =SUMPRODUCT(('Compras Cartão'!$C$5:$C$204=Config!$A$12)*('Compras Cartão'!$F$5:$F$204<=D$4)*('Compras Cartão'!$H$5:$H$204>=D$4)*('Compras Cartão'!$G$5:$G$204)) -> 0 | E7: =SUMPRODUCT(('Compras Cartão'!$C$5:$C$204=Config!$A$12)*('Compras Cartão'!$F$5:$F$204<=E$4)*('Compras Cartão'!$H$5:$H$204>=E$4)*('Compras Cartão'!$G$5:$G$204)) -> 0 | F7: =SUMPRODUCT(('Compras Cartão'!$C$5:$C$204=Config!$A$12)*('Compras Cartão'!$F$5:$F$204<=F$4)*('Compras Cartão'!$H$5:$H$204>=F$4)*('Compras Cartão'!$G$5:$G$204)) -> 0 | G7: =SUMPRODUCT(('Compras Cartão'!$C$5:$C$204=Config!$A$12)*('Compras Cartão'!$F$5:$F$204<=G$4)*('Compras Cartão'!$H$5:$H$204>=G$4)*('Compras Cartão'!$G$5:$G$204)) -> 0 | H7: =SUMPRODUCT(('Compras Cartão'!$C$5:$C$204=Config!$A$12)*('Compras Cartão'!$F$5:$F$204<=H$4)*('Compras Cartão'!$H$5:$H$204>=H$4)*('Compras Cartão'!$G$5:$G$204)) -> 0 | I7: =SUMPRODUCT(('Compras Cartão'!$C$5:$C$204=Config!$A$12)*('Compras Cartão'!$F$5:$F$204<=I$4)*('Compras Cartão'!$H$5:$H$204>=I$4)*('Compras Cartão'!$G$5:$G$204)) -> 0 | J7: =SUMPRODUCT(('Compras Cartão'!$C$5:$C$204=Config!$A$12)*('Compras Cartão'!$F$5:$F$204<=J$4)*('Compras Cartão'!$H$5:$H$204>=J$4)*('Compras Cartão'!$G$5:$G$204)) -> 0 | K7: =SUMPRODUCT(('Compras Cartão'!$C$5:$C$204=Config!$A$12)*('Compras Cartão'!$F$5:$F$204<=K$4)*('Compras Cartão'!$H$5:$H$204>=K$4)*('Compras Cartão'!$G$5:$G$204)) -> 0 | ... R7: =SUMPRODUCT(('Compras Cartão'!$C$5:$C$204=Config!$A$12)*('Compras Cartão'!$F$5:$F$204<=R$4)*('Compras Cartão'!$H$5:$H$204>=R$4)*('Compras Cartão'!$G$5:$G$204)) -> 0 | S7: =SUM(D7:R7) -> 0
A8: Novas compras - Pedro | B8: Cartão | C8: automático | D8: =SUMPRODUCT(('Compras Cartão'!$C$5:$C$204=Config!$A$13)*('Compras Cartão'!$F$5:$F$204<=D$4)*('Compras Cartão'!$H$5:$H$204>=D$4)*('Compras Cartão'!$G$5:$G$204)) -> 0 | E8: =SUMPRODUCT(('Compras Cartão'!$C$5:$C$204=Config!$A$13)*('Compras Cartão'!$F$5:$F$204<=E$4)*('Compras Cartão'!$H$5:$H$204>=E$4)*('Compras Cartão'!$G$5:$G$204)) -> 0 | F8: =SUMPRODUCT(('Compras Cartão'!$C$5:$C$204=Config!$A$13)*('Compras Cartão'!$F$5:$F$204<=F$4)*('Compras Cartão'!$H$5:$H$204>=F$4)*('Compras Cartão'!$G$5:$G$204)) -> 0 | G8: =SUMPRODUCT(('Compras Cartão'!$C$5:$C$204=Config!$A$13)*('Compras Cartão'!$F$5:$F$204<=G$4)*('Compras Cartão'!$H$5:$H$204>=G$4)*('Compras Cartão'!$G$5:$G$204)) -> 0 | H8: =SUMPRODUCT(('Compras Cartão'!$C$5:$C$204=Config!$A$13)*('Compras Cartão'!$F$5:$F$204<=H$4)*('Compras Cartão'!$H$5:$H$204>=H$4)*('Compras Cartão'!$G$5:$G$204)) -> 0 | I8: =SUMPRODUCT(('Compras Cartão'!$C$5:$C$204=Config!$A$13)*('Compras Cartão'!$F$5:$F$204<=I$4)*('Compras Cartão'!$H$5:$H$204>=I$4)*('Compras Cartão'!$G$5:$G$204)) -> 0 | J8: =SUMPRODUCT(('Compras Cartão'!$C$5:$C$204=Config!$A$13)*('Compras Cartão'!$F$5:$F$204<=J$4)*('Compras Cartão'!$H$5:$H$204>=J$4)*('Compras Cartão'!$G$5:$G$204)) -> 0 | K8: =SUMPRODUCT(('Compras Cartão'!$C$5:$C$204=Config!$A$13)*('Compras Cartão'!$F$5:$F$204<=K$4)*('Compras Cartão'!$H$5:$H$204>=K$4)*('Compras Cartão'!$G$5:$G$204)) -> 0 | ... R8: =SUMPRODUCT(('Compras Cartão'!$C$5:$C$204=Config!$A$13)*('Compras Cartão'!$F$5:$F$204<=R$4)*('Compras Cartão'!$H$5:$H$204>=R$4)*('Compras Cartão'!$G$5:$G$204)) -> 0 | S8: =SUM(D8:R8) -> 0
A9: TOTAL JESSICA | D9: =D5+D7 -> 3126.15 | E9: =E5+E7 -> 1319.86 | F9: =F5+F7 -> 659.7 | G9: =G5+G7 -> 365.14 | H9: =H5+H7 -> 81.48 | I9: =I5+I7 -> 52.41 | J9: =J5+J7 -> 52.41 | K9: =K5+K7 -> 52.41 | ... S9: =S5+S7 -> 5761.97
A10: TOTAL PEDRO | D10: =D6+D8 -> 3457.84 | E10: =E6+E8 -> 1052.14 | F10: =F6+F8 -> 827.8 | G10: =G6+G8 -> 677.64 | H10: =H6+H8 -> 622.65 | I10: =I6+I8 -> 614.04 | J10: =J6+J8 -> 488.21 | K10: =K6+K8 -> 488.21 | ... S10: =S6+S8 -> 8274.67
A11: TOTAL CARTÃO | D11: =D9+D10 -> 6583.99 | E11: =E9+E10 -> 2372 | F11: =F9+F10 -> 1487.5 | G11: =G9+G10 -> 1042.78 | H11: =H9+H10 -> 704.13 | I11: =I9+I10 -> 666.45 | J11: =J9+J10 -> 540.62 | K11: =K9+K10 -> 540.62 | ... S11: =S9+S10 -> 14036.64

Sheet Compras Cartão
A1: Novas compras no cartão
A2: Lance cada compra NOVA aqui; ela se distribui sozinha nos meses. Exemplo: 12/10/2026 | Tênis | Jessica | 600 | 3 | nov/26 (mês da 1ª fatura) | Roupas
A4: Data | B4: Descrição | C4: Quem | D4: Valor total | E4: Nº parcelas | F4: 1ª fatura (mês) | G4: Valor parcela | H4: Última fatura | I4: Categoria
G5: =IF(OR(D5="",E5="",N(E5)=0),0,D5/E5) -> 0 | H5: =IF(OR(F5="",E5=""),0,EDATE(F5,E5-1)) -> 0
G6: =IF(OR(D6="",E6="",N(E6)=0),0,D6/E6) -> 0 | H6: =IF(OR(F6="",E6=""),0,EDATE(F6,E6-1)) -> 0
G7: =IF(OR(D7="",E7="",N(E7)=0),0,D7/E7) -> 0 | H7: =IF(OR(F7="",E7=""),0,EDATE(F7,E7-1)) -> 0
G8: =IF(OR(D8="",E8="",N(E8)=0),0,D8/E8) -> 0 | H8: =IF(OR(F8="",E8=""),0,EDATE(F8,E8-1)) -> 0
G9: =IF(OR(D9="",E9="",N(E9)=0),0,D9/E9) -> 0 | H9: =IF(OR(F9="",E9=""),0,EDATE(F9,E9-1)) -> 0
G10: =IF(OR(D10="",E10="",N(E10)=0),0,D10/E10) -> 0 | H10: =IF(OR(F10="",E10=""),0,EDATE(F10,E10-1)) -> 0
G11: =IF(OR(D11="",E11="",N(E11)=0),0,D11/E11) -> 0 | H11: =IF(OR(F11="",E11=""),0,EDATE(F11,E11-1)) -> 0
G12: =IF(OR(D12="",E12="",N(E12)=0),0,D12/E12) -> 0 | H12: =IF(OR(F12="",E12=""),0,EDATE(F12,E12-1)) -> 0
G13: =IF(OR(D13="",E13="",N(E13)=0),0,D13/E13) -> 0 | H13: =IF(OR(F13="",E13=""),0,EDATE(F13,E13-1)) -> 0
G14: =IF(OR(D14="",E14="",N(E14)=0),0,D14/E14) -> 0 | H14: =IF(OR(F14="",E14=""),0,EDATE(F14,E14-1)) -> 0
G15: =IF(OR(D15="",E15="",N(E15)=0),0,D15/E15) -> 0 | H15: =IF(OR(F15="",E15=""),0,EDATE(F15,E15-1)) -> 0
G16: =IF(OR(D16="",E16="",N(E16)=0),0,D16/E16) -> 0 | H16: =IF(OR(F16="",E16=""),0,EDATE(F16,E16-1)) -> 0
... G204: =IF(OR(D204="",E204="",N(E204)=0),0,D204/E204) -> 0 | H204: =IF(OR(F204="",E204=""),0,EDATE(F204,E204-1)) -> 0

Sheet Mercado & Alelo
A1: Mercado & Alelo
A2: Células AMARELAS com texto AZUL = você preenche/edita. O resto é fórmula (não apague). O Alelo abate primeiro do mercado; só o que passar sai do salário.
A4: Item | B4: Categoria | C4: Obs. | D4: 46296 | E4: 46327 | F4: 46357 | G4: 46388 | H4: 46419 | I4: 46447 | J4: 46478 | K4: 46508 | L4: 46539 | M4: 46569 | N4: 46600 | O4: 46631 | P4: 46661 | Q4: 46692 | R4: 46722 | S4: Total
A5: Orçamento de mercado do mês | B5: Mercado | C5: defina quanto gastam | D5: 0 | E5: 0 | F5: 0 | G5: 0 | H5: 0 | I5: 0 | J5: 0 | K5: 0 | L5: 0 | M5: 0 | N5: 0 | O5: 0 | P5: 0 | Q5: 0 | R5: 0 | S5: =SUM(D5:R5) -> 0
A6: Alelo recebido | B6: Benefício | C6: preencher quando começar | D6: 0 | E6: 0 | F6: 0 | G6: 0 | H6: 0 | I6: 0 | J6: 0 | K6: 0 | L6: 0 | M6: 0 | N6: 0 | O6: 0 | P6: 0 | Q6: 0 | R6: 0 | S6: =SUM(D6:R6) -> 0
A7: Mercado coberto pelo Alelo | D7: =MIN(D5,D6) -> 0 | E7: =MIN(E5,E6) -> 0 | F7: =MIN(F5,F6) -> 0 | G7: =MIN(G5,G6) -> 0 | H7: =MIN(H5,H6) -> 0 | I7: =MIN(I5,I6) -> 0 | J7: =MIN(J5,J6) -> 0 | K7: =MIN(K5,K6) -> 0 | ... R7: =MIN(R5,R6) -> 0 | S7: =SUM(D7:R7) -> 0
A8: Mercado pago do salário | D8: =MAX(0,D5-D6) -> 0 | E8: =MAX(0,E5-E6) -> 0 | F8: =MAX(0,F5-F6) -> 0 | G8: =MAX(0,G5-G6) -> 0 | H8: =MAX(0,H5-H6) -> 0 | I8: =MAX(0,I5-I6) -> 0 | J8: =MAX(0,J5-J6) -> 0 | K8: =MAX(0,K5-K6) -> 0 | ... R8: =MAX(0,R5-R6) -> 0 | S8: =SUM(D8:R8) -> 0
A9: Alelo que sobrou | D9: =MAX(0,D6-D5) -> 0 | E9: =MAX(0,E6-E5) -> 0 | F9: =MAX(0,F6-F5) -> 0 | G9: =MAX(0,G6-G5) -> 0 | H9: =MAX(0,H6-H5) -> 0 | I9: =MAX(0,I6-I5) -> 0 | J9: =MAX(0,J6-J5) -> 0 | K9: =MAX(0,K6-K5) -> 0 | ... R9: =MAX(0,R6-R5) -> 0 | S9: =SUM(D9:R9) -> 0

Sheet Provisões
A1: Provisões — gastos anuais (IPTU, IPVA...)
A2: Em vez do susto no mês do boleto, a planilha separa um pouco por mês até a data. Células AMARELAS com texto AZUL = você preenche/edita. O resto é fórmula (não apague).
A4: Gasto anual | B4: Valor total | C4: Mês de pagamento | D4: Começar a guardar em | E4: Nº de meses | F4: Guardar por mês | G4: Obs.
A5: IPTU da casa 2027 | B5: 800 | C5: 46419 | D5: 46327 | E5: =IF(OR(C5="",D5=""),0,(YEAR(C5)-YEAR(D5))*12+MONTH(C5)-MONTH(D5)+1) -> 4 | F5: =IF(E5<=0,0,B5/E5) -> 200 | G5: ESTIMATIVA - troque pelo valor do carnê
A6: IPVA + licenciamento da moto 2027 | B6: 350 | C6: 46388 | D6: 46327 | E6: =IF(OR(C6="",D6=""),0,(YEAR(C6)-YEAR(D6))*12+MONTH(C6)-MONTH(D6)+1) -> 3 | F6: =IF(E6<=0,0,B6/E6) -> 116.66667 | G6: ESTIMATIVA - troque pelo valor real
E7: =IF(OR(C7="",D7=""),0,(YEAR(C7)-YEAR(D7))*12+MONTH(C7)-MONTH(D7)+1) -> 0 | F7: =IF(E7<=0,0,B7/E7) -> 0
E8: =IF(OR(C8="",D8=""),0,(YEAR(C8)-YEAR(D8))*12+MONTH(C8)-MONTH(D8)+1) -> 0 | F8: =IF(E8<=0,0,B8/E8) -> 0
E9: =IF(OR(C9="",D9=""),0,(YEAR(C9)-YEAR(D9))*12+MONTH(C9)-MONTH(D9)+1) -> 0 | F9: =IF(E9<=0,0,B9/E9) -> 0
E10: =IF(OR(C10="",D10=""),0,(YEAR(C10)-YEAR(D10))*12+MONTH(C10)-MONTH(D10)+1) -> 0 | F10: =IF(E10<=0,0,B10/E10) -> 0
E11: =IF(OR(C11="",D11=""),0,(YEAR(C11)-YEAR(D11))*12+MONTH(C11)-MONTH(D11)+1) -> 0 | F11: =IF(E11<=0,0,B11/E11) -> 0
E12: =IF(OR(C12="",D12=""),0,(YEAR(C12)-YEAR(D12))*12+MONTH(C12)-MONTH(D12)+1) -> 0 | F12: =IF(E12<=0,0,B12/E12) -> 0
A14: Quanto separar em cada mês (automático)
A15: Gasto anual | B15: 46296 | C15: 46327 | D15: 46357 | E15: 46388 | F15: 46419 | G15: 46447 | H15: 46478 | I15: 46508 | J15: 46539 | K15: 46569 | L15: 46600 | M15: 46631 | N15: 46661 | O15: 46692 | P15: 46722 | Q15: Total
A16: =IF(A5="","",A5) -> IPTU da casa 2027 | B16: =IF(AND(B$15>=$D$5,B$15<=$C$5),$F$5,0) -> 0 | C16: =IF(AND(C$15>=$D$5,C$15<=$C$5),$F$5,0) -> 200 | D16: =IF(AND(D$15>=$D$5,D$15<=$C$5),$F$5,0) -> 200 | E16: =IF(AND(E$15>=$D$5,E$15<=$C$5),$F$5,0) -> 200 | F16: =IF(AND(F$15>=$D$5,F$15<=$C$5),$F$5,0) -> 200 | G16: =IF(AND(G$15>=$D$5,G$15<=$C$5),$F$5,0) -> 0 | H16: =IF(AND(H$15>=$D$5,H$15<=$C$5),$F$5,0) -> 0 | I16: =IF(AND(I$15>=$D$5,I$15<=$C$5),$F$5,0) -> 0 | ... P16: =IF(AND(P$15>=$D$5,P$15<=$C$5),$F$5,0) -> 0 | Q16: =SUM(B16:P16) -> 800
A17: =IF(A6="","",A6) -> IPVA + licenciamento da moto 2027 | B17: =IF(AND(B$15>=$D$6,B$15<=$C$6),$F$6,0) -> 0 | C17: =IF(AND(C$15>=$D$6,C$15<=$C$6),$F$6,0) -> 116.66667 | D17: =IF(AND(D$15>=$D$6,D$15<=$C$6),$F$6,0) -> 116.66667 | E17: =IF(AND(E$15>=$D$6,E$15<=$C$6),$F$6,0) -> 116.66667 | F17: =IF(AND(F$15>=$D$6,F$15<=$C$6),$F$6,0) -> 0 | G17: =IF(AND(G$15>=$D$6,G$15<=$C$6),$F$6,0) -> 0 | H17: =IF(AND(H$15>=$D$6,H$15<=$C$6),$F$6,0) -> 0 | I17: =IF(AND(I$15>=$D$6,I$15<=$C$6),$F$6,0) -> 0 | ... P17: =IF(AND(P$15>=$D$6,P$15<=$C$6),$F$6,0) -> 0 | Q17: =SUM(B17:P17) -> 350
A18: =IF(A7="","",A7) | B18: =IF(AND(B$15>=$D$7,B$15<=$C$7),$F$7,0) -> 0 | C18: =IF(AND(C$15>=$D$7,C$15<=$C$7),$F$7,0) -> 0 | D18: =IF(AND(D$15>=$D$7,D$15<=$C$7),$F$7,0) -> 0 | E18: =IF(AND(E$15>=$D$7,E$15<=$C$7),$F$7,0) -> 0 | F18: =IF(AND(F$15>=$D$7,F$15<=$C$7),$F$7,0) -> 0 | G18: =IF(AND(G$15>=$D$7,G$15<=$C$7),$F$7,0) -> 0 | H18: =IF(AND(H$15>=$D$7,H$15<=$C$7),$F$7,0) -> 0 | I18: =IF(AND(I$15>=$D$7,I$15<=$C$7),$F$7,0) -> 0 | ... P18: =IF(AND(P$15>=$D$7,P$15<=$C$7),$F$7,0) -> 0 | Q18: =SUM(B18:P18) -> 0
A19: =IF(A8="","",A8) | B19: =IF(AND(B$15>=$D$8,B$15<=$C$8),$F$8,0) -> 0 | C19: =IF(AND(C$15>=$D$8,C$15<=$C$8),$F$8,0) -> 0 | D19: =IF(AND(D$15>=$D$8,D$15<=$C$8),$F$8,0) -> 0 | E19: =IF(AND(E$15>=$D$8,E$15<=$C$8),$F$8,0) -> 0 | F19: =IF(AND(F$15>=$D$8,F$15<=$C$8),$F$8,0) -> 0 | G19: =IF(AND(G$15>=$D$8,G$15<=$C$8),$F$8,0) -> 0 | H19: =IF(AND(H$15>=$D$8,H$15<=$C$8),$F$8,0) -> 0 | I19: =IF(AND(I$15>=$D$8,I$15<=$C$8),$F$8,0) -> 0 | ... P19: =IF(AND(P$15>=$D$8,P$15<=$C$8),$F$8,0) -> 0 | Q19: =SUM(B19:P19) -> 0
A20: =IF(A9="","",A9) | B20: =IF(AND(B$15>=$D$9,B$15<=$C$9),$F$9,0) -> 0 | C20: =IF(AND(C$15>=$D$9,C$15<=$C$9),$F$9,0) -> 0 | D20: =IF(AND(D$15>=$D$9,D$15<=$C$9),$F$9,0) -> 0 | E20: =IF(AND(E$15>=$D$9,E$15<=$C$9),$F$9,0) -> 0 | F20: =IF(AND(F$15>=$D$9,F$15<=$C$9),$F$9,0) -> 0 | G20: =IF(AND(G$15>=$D$9,G$15<=$C$9),$F$9,0) -> 0 | H20: =IF(AND(H$15>=$D$9,H$15<=$C$9),$F$9,0) -> 0 | I20: =IF(AND(I$15>=$D$9,I$15<=$C$9),$F$9,0) -> 0 | ... P20: =IF(AND(P$15>=$D$9,P$15<=$C$9),$F$9,0) -> 0 | Q20: =SUM(B20:P20) -> 0
A21: =IF(A10="","",A10) | B21: =IF(AND(B$15>=$D$10,B$15<=$C$10),$F$10,0) -> 0 | C21: =IF(AND(C$15>=$D$10,C$15<=$C$10),$F$10,0) -> 0 | D21: =IF(AND(D$15>=$D$10,D$15<=$C$10),$F$10,0) -> 0 | E21: =IF(AND(E$15>=$D$10,E$15<=$C$10),$F$10,0) -> 0 | F21: =IF(AND(F$15>=$D$10,F$15<=$C$10),$F$10,0) -> 0 | G21: =IF(AND(G$15>=$D$10,G$15<=$C$10),$F$10,0) -> 0 | H21: =IF(AND(H$15>=$D$10,H$15<=$C$10),$F$10,0) -> 0 | I21: =IF(AND(I$15>=$D$10,I$15<=$C$10),$F$10,0) -> 0 | ... P21: =IF(AND(P$15>=$D$10,P$15<=$C$10),$F$10,0) -> 0 | Q21: =SUM(B21:P21) -> 0
A22: =IF(A11="","",A11) | B22: =IF(AND(B$15>=$D$11,B$15<=$C$11),$F$11,0) -> 0 | C22: =IF(AND(C$15>=$D$11,C$15<=$C$11),$F$11,0) -> 0 | D22: =IF(AND(D$15>=$D$11,D$15<=$C$11),$F$11,0) -> 0 | E22: =IF(AND(E$15>=$D$11,E$15<=$C$11),$F$11,0) -> 0 | F22: =IF(AND(F$15>=$D$11,F$15<=$C$11),$F$11,0) -> 0 | G22: =IF(AND(G$15>=$D$11,G$15<=$C$11),$F$11,0) -> 0 | H22: =IF(AND(H$15>=$D$11,H$15<=$C$11),$F$11,0) -> 0 | I22: =IF(AND(I$15>=$D$11,I$15<=$C$11),$F$11,0) -> 0 | ... P22: =IF(AND(P$15>=$D$11,P$15<=$C$11),$F$11,0) -> 0 | Q22: =SUM(B22:P22) -> 0
A23: =IF(A12="","",A12) | B23: =IF(AND(B$15>=$D$12,B$15<=$C$12),$F$12,0) -> 0 | C23: =IF(AND(C$15>=$D$12,C$15<=$C$12),$F$12,0) -> 0 | D23: =IF(AND(D$15>=$D$12,D$15<=$C$12),$F$12,0) -> 0 | E23: =IF(AND(E$15>=$D$12,E$15<=$C$12),$F$12,0) -> 0 | F23: =IF(AND(F$15>=$D$12,F$15<=$C$12),$F$12,0) -> 0 | G23: =IF(AND(G$15>=$D$12,G$15<=$C$12),$F$12,0) -> 0 | H23: =IF(AND(H$15>=$D$12,H$15<=$C$12),$F$12,0) -> 0 | I23: =IF(AND(I$15>=$D$12,I$15<=$C$12),$F$12,0) -> 0 | ... P23: =IF(AND(P$15>=$D$12,P$15<=$C$12),$F$12,0) -> 0 | Q23: =SUM(B23:P23) -> 0
A24: TOTAL A SEPARAR | B24: =SUM(B16:B23) -> 0 | C24: =SUM(C16:C23) -> 316.66667 | D24: =SUM(D16:D23) -> 316.66667 | E24: =SUM(E16:E23) -> 316.66667 | F24: =SUM(F16:F23) -> 200 | G24: =SUM(G16:G23) -> 0 | H24: =SUM(H16:H23) -> 0 | I24: =SUM(I16:I23) -> 0 | ... Q24: =SUM(Q16:Q23) -> 1150

Sheet Metas
A1: Metas de economia
A2: Células AMARELAS com texto AZUL = você preenche/edita. O resto é fórmula (não apague). Ainda sem valor definido? Deixe 0 — o dashboard mostra quanto dá para juntar no ritmo atual.
A4: Meta | B4: Valor alvo | C4: Prazo (mês) | D4: Já guardado antes | E4: Começar em | F4: Meses | G4: Precisa guardar/mês | H4: Guardado até agora | I4: % atingido | J4: Falta
A5: Reserva do casal até dez/27 | B5: 0 | C5: 46722 | D5: 0 | E5: 46327 | F5: =IF(OR(C5="",E5=""),0,(YEAR(C5)-YEAR(E5))*12+MONTH(C5)-MONTH(E5)+1) -> 14 | G5: =IF(F5<=0,0,MAX(0,B5-D5)/F5) -> 0 | H5: =N(D5)+Q14 -> 0 | I5: =IF(N(B5)=0,0,MIN(1,H5/B5)) -> 0 | J5: =MAX(0,N(B5)-H5) -> 0
F6: =IF(OR(C6="",E6=""),0,(YEAR(C6)-YEAR(E6))*12+MONTH(C6)-MONTH(E6)+1) -> 0 | G6: =IF(F6<=0,0,MAX(0,B6-D6)/F6) -> 0 | H6: =N(D6)+Q15 -> 0 | I6: =IF(N(B6)=0,0,MIN(1,H6/B6)) -> 0 | J6: =MAX(0,N(B6)-H6) -> 0
F7: =IF(OR(C7="",E7=""),0,(YEAR(C7)-YEAR(E7))*12+MONTH(C7)-MONTH(E7)+1) -> 0 | G7: =IF(F7<=0,0,MAX(0,B7-D7)/F7) -> 0 | H7: =N(D7)+Q16 -> 0 | I7: =IF(N(B7)=0,0,MIN(1,H7/B7)) -> 0 | J7: =MAX(0,N(B7)-H7) -> 0
F8: =IF(OR(C8="",E8=""),0,(YEAR(C8)-YEAR(E8))*12+MONTH(C8)-MONTH(E8)+1) -> 0 | G8: =IF(F8<=0,0,MAX(0,B8-D8)/F8) -> 0 | H8: =N(D8)+Q17 -> 0 | I8: =IF(N(B8)=0,0,MIN(1,H8/B8)) -> 0 | J8: =MAX(0,N(B8)-H8) -> 0
F9: =IF(OR(C9="",E9=""),0,(YEAR(C9)-YEAR(E9))*12+MONTH(C9)-MONTH(E9)+1) -> 0 | G9: =IF(F9<=0,0,MAX(0,B9-D9)/F9) -> 0 | H9: =N(D9)+Q18 -> 0 | I9: =IF(N(B9)=0,0,MIN(1,H9/B9)) -> 0 | J9: =MAX(0,N(B9)-H9) -> 0
F10: =IF(OR(C10="",E10=""),0,(YEAR(C10)-YEAR(E10))*12+MONTH(C10)-MONTH(E10)+1) -> 0 | G10: =IF(F10<=0,0,MAX(0,B10-D10)/F10) -> 0 | H10: =N(D10)+Q19 -> 0 | I10: =IF(N(B10)=0,0,MIN(1,H10/B10)) -> 0 | J10: =MAX(0,N(B10)-H10) -> 0
A12: Registro mensal: quanto vocês REALMENTE guardaram em cada meta
A13: Meta | B13: 46296 | C13: 46327 | D13: 46357 | E13: 46388 | F13: 46419 | G13: 46447 | H13: 46478 | I13: 46508 | J13: 46539 | K13: 46569 | L13: 46600 | M13: 46631 | N13: 46661 | O13: 46692 | P13: 46722 | Q13: Total
A14: =IF(A5="","(meta 1)",A5) -> Reserva do casal até dez/27 | Q14: =SUM(B14:P14) -> 0
A15: =IF(A6="","(meta 2)",A6) -> (meta 2) | Q15: =SUM(B15:P15) -> 0
A16: =IF(A7="","(meta 3)",A7) -> (meta 3) | Q16: =SUM(B16:P16) -> 0
A17: =IF(A8="","(meta 4)",A8) -> (meta 4) | Q17: =SUM(B17:P17) -> 0
A18: =IF(A9="","(meta 5)",A9) -> (meta 5) | Q18: =SUM(B18:P18) -> 0
A19: =IF(A10="","(meta 6)",A10) -> (meta 6) | Q19: =SUM(B19:P19) -> 0
A20: TOTAL GUARDADO NO MÊS | B20: =SUM(B14:B19) -> 0 | C20: =SUM(C14:C19) -> 0 | D20: =SUM(D14:D19) -> 0 | E20: =SUM(E14:E19) -> 0 | F20: =SUM(F14:F19) -> 0 | G20: =SUM(G14:G19) -> 0 | H20: =SUM(H14:H19) -> 0 | I20: =SUM(I14:I19) -> 0 | ... Q20: =SUM(Q14:Q19) -> 0

Sheet Config
A1: Configurações
A2: Células AMARELAS com texto AZUL = você preenche/edita. O resto é fórmula (não apague).
A4: Parâmetro | B4: Valor | C4: Observação
A5: % da sobra para GUARDAR (meta) | B5: 0.3 | C5: Regra de divisão do que sobra depois de todas as contas.
A6: % da sobra para RESERVA de novas coisas | B6: 0.2 | C6: Colchão para compras novas, imprevistos, presentes...
A7: % da sobra LIVRE para gastar | B7: =1-B5-B6 -> 0.5 | C7: Calculado: 100% menos os dois acima.
A8: Alerta: comprometimento máximo saudável | B8: 0.7 | C8: Acima disso (em % da receita) o mês fica em ALERTA.
A11: Pessoas (usadas na aba Compras Cartão)
A12: Jessica
A13: Pedro
